not_so_evil_package_spaceylad/__init__.py
not_so_evil_package_spaceylad/execute.py
not_so_evil_package_spaceylad-0.0.7.dist-info/METADATA
not_so_evil_package_spaceylad-0.0.7.dist-info/WHEEL
not_so_evil_package_spaceylad-0.0.7.dist-info/licenses/LICENSE
not_so_evil_package_spaceylad-0.0.7.dist-info/RECORD
